<?xml version="1.0" encoding="UTF-8"?>
<!DOCTYPE mapper PUBLIC "-//mybatis.org//DTD Mapper 3.0//EN" "http://mybatis.org/dtd/mybatis-3-mapper.dtd">
<mapper namespace="com.ecom.dao.example.BaseStationMapper">
  <resultMap id="BaseResultMap" type="com.ecom.entity.example.BaseStation">
    <!--
      WARNING - @mbggenerated
      This element is automatically generated by MyBatis Generator, do not modify.
    -->
    <id column="id" jdbcType="INTEGER" property="id" />
    <result column="no" jdbcType="INTEGER" property="no" />
    <result column="area" jdbcType="VARCHAR" property="area" />
    <result column="type" jdbcType="VARCHAR" property="type" />
    <result column="format" jdbcType="VARCHAR" property="format" />
    <result column="name" jdbcType="VARCHAR" property="name" />
    <result column="enb_id" jdbcType="INTEGER" property="enbId" />
    <result column="enb_name" jdbcType="VARCHAR" property="enbName" />
    <result column="cell_name" jdbcType="VARCHAR" property="cellName" />
    <result column="longitude" jdbcType="DECIMAL" property="longitude" />
    <result column="latitude" jdbcType="DECIMAL" property="latitude" />
    <result column="tac" jdbcType="VARCHAR" property="tac" />
    <result column="swversion" jdbcType="VARCHAR" property="swversion" />
    <result column="ip" jdbcType="VARCHAR" property="ip" />
    <result column="mme" jdbcType="VARCHAR" property="mme" />
    <result column="license_user" jdbcType="VARCHAR" property="licenseUser" />
  </resultMap>
  <sql id="Base_Column_List">
    <!--
      WARNING - @mbggenerated
      This element is automatically generated by MyBatis Generator, do not modify.
    -->
    id, no, area, type, format, name, enb_id, enb_name, cell_name, longitude, latitude, 
    tac, swversion, ip, mme, license_user
  </sql>
  <select id="selectByPrimaryKey" parameterType="java.lang.Integer" resultMap="BaseResultMap">
    <!--
      WARNING - @mbggenerated
      This element is automatically generated by MyBatis Generator, do not modify.
    -->
    select 
    <include refid="Base_Column_List" />
    from base_station
    where id = #{id,jdbcType=INTEGER}
  </select>
  <delete id="deleteByPrimaryKey" parameterType="java.lang.Integer">
    <!--
      WARNING - @mbggenerated
      This element is automatically generated by MyBatis Generator, do not modify.
    -->
    delete from base_station
    where id = #{id,jdbcType=INTEGER}
  </delete>
  <insert id="insert" parameterType="com.ecom.entity.example.BaseStation">
    <!--
      WARNING - @mbggenerated
      This element is automatically generated by MyBatis Generator, do not modify.
    -->
    insert into base_station (id, no, area, 
      type, format, name, 
      enb_id, enb_name, cell_name, 
      longitude, latitude, tac, 
      swversion, ip, mme, 
      license_user)
    values (#{id,jdbcType=INTEGER}, #{no,jdbcType=INTEGER}, #{area,jdbcType=VARCHAR}, 
      #{type,jdbcType=VARCHAR}, #{format,jdbcType=VARCHAR}, #{name,jdbcType=VARCHAR}, 
      #{enbId,jdbcType=INTEGER}, #{enbName,jdbcType=VARCHAR}, #{cellName,jdbcType=VARCHAR}, 
      #{longitude,jdbcType=DECIMAL}, #{latitude,jdbcType=DECIMAL}, #{tac,jdbcType=VARCHAR}, 
      #{swversion,jdbcType=VARCHAR}, #{ip,jdbcType=VARCHAR}, #{mme,jdbcType=VARCHAR}, 
      #{licenseUser,jdbcType=VARCHAR})
  </insert>
  <insert id="insertSelective" parameterType="com.ecom.entity.example.BaseStation">
    <!--
      WARNING - @mbggenerated
      This element is automatically generated by MyBatis Generator, do not modify.
    -->
    insert into base_station
    <trim prefix="(" suffix=")" suffixOverrides=",">
      <if test="id != null">
        id,
      </if>
      <if test="no != null">
        no,
      </if>
      <if test="area != null">
        area,
      </if>
      <if test="type != null">
        type,
      </if>
      <if test="format != null">
        format,
      </if>
      <if test="name != null">
        name,
      </if>
      <if test="enbId != null">
        enb_id,
      </if>
      <if test="enbName != null">
        enb_name,
      </if>
      <if test="cellName != null">
        cell_name,
      </if>
      <if test="longitude != null">
        longitude,
      </if>
      <if test="latitude != null">
        latitude,
      </if>
      <if test="tac != null">
        tac,
      </if>
      <if test="swversion != null">
        swversion,
      </if>
      <if test="ip != null">
        ip,
      </if>
      <if test="mme != null">
        mme,
      </if>
      <if test="licenseUser != null">
        license_user,
      </if>
    </trim>
    <trim prefix="values (" suffix=")" suffixOverrides=",">
      <if test="id != null">
        #{id,jdbcType=INTEGER},
      </if>
      <if test="no != null">
        #{no,jdbcType=INTEGER},
      </if>
      <if test="area != null">
        #{area,jdbcType=VARCHAR},
      </if>
      <if test="type != null">
        #{type,jdbcType=VARCHAR},
      </if>
      <if test="format != null">
        #{format,jdbcType=VARCHAR},
      </if>
      <if test="name != null">
        #{name,jdbcType=VARCHAR},
      </if>
      <if test="enbId != null">
        #{enbId,jdbcType=INTEGER},
      </if>
      <if test="enbName != null">
        #{enbName,jdbcType=VARCHAR},
      </if>
      <if test="cellName != null">
        #{cellName,jdbcType=VARCHAR},
      </if>
      <if test="longitude != null">
        #{longitude,jdbcType=DECIMAL},
      </if>
      <if test="latitude != null">
        #{latitude,jdbcType=DECIMAL},
      </if>
      <if test="tac != null">
        #{tac,jdbcType=VARCHAR},
      </if>
      <if test="swversion != null">
        #{swversion,jdbcType=VARCHAR},
      </if>
      <if test="ip != null">
        #{ip,jdbcType=VARCHAR},
      </if>
      <if test="mme != null">
        #{mme,jdbcType=VARCHAR},
      </if>
      <if test="licenseUser != null">
        #{licenseUser,jdbcType=VARCHAR},
      </if>
    </trim>
  </insert>
  <update id="updateByPrimaryKeySelective" parameterType="com.ecom.entity.example.BaseStation">
    <!--
      WARNING - @mbggenerated
      This element is automatically generated by MyBatis Generator, do not modify.
    -->
    update base_station
    <set>
      <if test="no != null">
        no = #{no,jdbcType=INTEGER},
      </if>
      <if test="area != null">
        area = #{area,jdbcType=VARCHAR},
      </if>
      <if test="type != null">
        type = #{type,jdbcType=VARCHAR},
      </if>
      <if test="format != null">
        format = #{format,jdbcType=VARCHAR},
      </if>
      <if test="name != null">
        name = #{name,jdbcType=VARCHAR},
      </if>
      <if test="enbId != null">
        enb_id = #{enbId,jdbcType=INTEGER},
      </if>
      <if test="enbName != null">
        enb_name = #{enbName,jdbcType=VARCHAR},
      </if>
      <if test="cellName != null">
        cell_name = #{cellName,jdbcType=VARCHAR},
      </if>
      <if test="longitude != null">
        longitude = #{longitude,jdbcType=DECIMAL},
      </if>
      <if test="latitude != null">
        latitude = #{latitude,jdbcType=DECIMAL},
      </if>
      <if test="tac != null">
        tac = #{tac,jdbcType=VARCHAR},
      </if>
      <if test="swversion != null">
        swversion = #{swversion,jdbcType=VARCHAR},
      </if>
      <if test="ip != null">
        ip = #{ip,jdbcType=VARCHAR},
      </if>
      <if test="mme != null">
        mme = #{mme,jdbcType=VARCHAR},
      </if>
      <if test="licenseUser != null">
        license_user = #{licenseUser,jdbcType=VARCHAR},
      </if>
    </set>
    where id = #{id,jdbcType=INTEGER}
  </update>
  <update id="updateByPrimaryKey" parameterType="com.ecom.entity.example.BaseStation">
    <!--
      WARNING - @mbggenerated
      This element is automatically generated by MyBatis Generator, do not modify.
    -->
    update base_station
    set no = #{no,jdbcType=INTEGER},
      area = #{area,jdbcType=VARCHAR},
      type = #{type,jdbcType=VARCHAR},
      format = #{format,jdbcType=VARCHAR},
      name = #{name,jdbcType=VARCHAR},
      enb_id = #{enbId,jdbcType=INTEGER},
      enb_name = #{enbName,jdbcType=VARCHAR},
      cell_name = #{cellName,jdbcType=VARCHAR},
      longitude = #{longitude,jdbcType=DECIMAL},
      latitude = #{latitude,jdbcType=DECIMAL},
      tac = #{tac,jdbcType=VARCHAR},
      swversion = #{swversion,jdbcType=VARCHAR},
      ip = #{ip,jdbcType=VARCHAR},
      mme = #{mme,jdbcType=VARCHAR},
      license_user = #{licenseUser,jdbcType=VARCHAR}
    where id = #{id,jdbcType=INTEGER}
  </update>
</mapper>